LICENSE
async_web3/__init__.py
async_web3/contract.py
async_web3/main.py
async_web3/methods.py
async_web3/subscription.py
async_web3/transport.py
async_web3/types/__init__.py
async_web3-0.3.1.dist-info/LICENSE
async_web3-0.3.1.dist-info/WHEEL
async_web3-0.3.1.dist-info/METADATA
async_web3-0.3.1.dist-info/RECORD
