Metadata-Version: 2.1
Name: async-web3
Version: 0.3.1
Summary: Async Web3 library
Home-page: https://github.com/guanqun/async-web3.py
License: MIT
Keywords: ethereum,web3,asyncio
Author: Guanqun Lu
Author-email: guanqunlu@outlook.com
Requires-Python: >=3.9,<4.0
Classifier: Development Status :: 4 - Beta
Classifier: Environment :: Other Environment
Classifier: Intended Audience :: Developers
Classifier: License :: OSI Approved :: MIT License
Classifier: Operating System :: OS Independent
Classifier: Programming Language :: Python
Classifier: Programming Language :: Python :: 3
Classifier: Programming Language :: Python :: 3.9
Classifier: Topic :: Software Development :: Libraries :: Python Modules
Requires-Dist: eth-abi (>=2.1.1,<3.0.0)
Requires-Dist: eth-brownie (>=1.14.6,<2.0.0)
Requires-Dist: eth-utils (>=1.10.0,<2.0.0)
Requires-Dist: pytest-asyncio (>=0.15.1,<0.16.0)
Requires-Dist: web3 (>=5.18.0,<6.0.0)
Requires-Dist: websockets (>=8.1.0,<9.0.0)
Project-URL: Repository, https://github.com/guanqun/async-web3.py
